[
  {
    "Расписание занятий\nна 2 семестр 2025-2026 учебного года.\nИнститут биотехнологии 2 курс": "Дни",
    "column_1": "Часы",
    "column_2": "Б-ТОП-21",
    "column_3": "Б-ТОП-22"
  },
  {
    "Расписание занятий\nна 2 семестр 2025-2026 учебного года.\nИнститут биотехнологии 2 курс": "",
    "column_1": "08.30-10.00",
    "column_2": "",
    "column_3": ""
  },
  {
    "Расписание занятий\nна 2 семестр 2025-2026 учебного года.\nИнститут биотехнологии 2 курс": "6\n2\n0\n2\n3.\n0\n3.\n2\nк\nи\nн\nь\nл\nе\nд\nе\nн\nо\nП",
    "column_1": "",
    "column_2": "",
    "column_3": ""
  },
  {
    "Расписание занятий\nна 2 семестр 2025-2026 учебного года.\nИнститут биотехнологии 2 курс": null,
    "column_1": "10.10-11.40",
    "column_2": "",
    "column_3": "пр.з. Организация и планирование производственной и\nсбытовой деятельности доц. Руднев М.Ю. ауд. 418"
  },
  {
    "Расписание занятий\nна 2 семестр 2025-2026 учебного года.\nИнститут биотехнологии 2 курс": null,
    "column_1": "12.00-13.30",
    "column_2": "ЭКЗАМЕН Иностранный язык\nИванова Л.М. ауд. С-404, Солотова Н.В. ауд. С-406",
    "column_3": "ЭКЗАМЕН Организация и планирование производственной и\nсбытовой деятельности доц. Руднев М.Ю. ауд. 418"
  },
  {
    "Расписание занятий\nна 2 семестр 2025-2026 учебного года.\nИнститут биотехнологии 2 курс": null,
    "column_1": "13.40-15.10",
    "column_2": "переезд на учебный комплекс №2",
    "column_3": null
  },
  {
    "Расписание занятий\nна 2 семестр 2025-2026 учебного года.\nИнститут биотехнологии 2 курс": null,
    "column_1": "15.20-16.50",
    "column_2": "лек. ИСТОРИЯ РОССИИ\nдоц. Федорова-Кузнецова И.В. учебный комплекс №2 ауд. 402",
    "column_3": null
  },
  {
    "Расписание занятий\nна 2 семестр 2025-2026 учебного года.\nИнститут биотехнологии 2 курс": null,
    "column_1": "17.00-18.30",
    "column_2": "пр.з. История России\nдоц. Федорова-Кузнецова И.В. УК №2 ауд. 402",
    "column_3": ""
  },
  {
    "Расписание занятий\nна 2 семестр 2025-2026 учебного года.\nИнститут биотехнологии 2 курс": "6\n2\n0\n2\n3.\n0\n4.\n2\nк\nи\nн\nр\nо\nт\nВ",
    "column_1": "08.30-10.00",
    "column_2": "пр.з. Организация и планирование производственной и\nсбытовой деятельности доц. Руднев М.Ю. ауд. 418",
    "column_3": ""
  },
  {
    "Расписание занятий\nна 2 семестр 2025-2026 учебного года.\nИнститут биотехнологии 2 курс": null,
    "column_1": "10.10-11.40",
    "column_2": "ЭКЗАМЕН Организация и планирование производственной\nи сбытовой деятельности доц. Руднев М.Ю. ауд. 418",
    "column_3": "пр.з. История России\nдоц. Федорова-Кузнецова И.В. ауд. Малая"
  },
  {
    "Расписание занятий\nна 2 семестр 2025-2026 учебного года.\nИнститут биотехнологии 2 курс": null,
    "column_1": "12.00-13.30",
    "column_2": "пр.з. История России\nдоц. Федорова-Кузнецова И.В. ауд. Малая",
    "column_3": "пр.з. История России\nдоц. Федорова-Кузнецова И.В. ауд. Малая"
  },
  {
    "Расписание занятий\nна 2 семестр 2025-2026 учебного года.\nИнститут биотехнологии 2 курс": null,
    "column_1": "13.40-15.10",
    "column_2": "ЗАЧЕТ Нормативное и метрологическое обеспечение услуг\nобщественного питания доц. Колотова Н.А. ауд. С-206",
    "column_3": "ЗАЧЕТ Нормативное и метрологическое обеспечение услуг\nобщественного питания доц. Колотова Н.А. ауд. С-206"
  },
  {
    "Расписание занятий\nна 2 семестр 2025-2026 учебного года.\nИнститут биотехнологии 2 курс": null,
    "column_1": "15.20-16.50",
    "column_2": "",
    "column_3": "ЭКЗАМЕН Иностранный язык\nИванова Л.М. ауд. С-404, Солотова Н.В. ауд. С-406"
  },
  {
    "Расписание занятий\nна 2 семестр 2025-2026 учебного года.\nИнститут биотехнологии 2 курс": null,
    "column_1": "17.00-18.30",
    "column_2": "",
    "column_3": ""
  },
  {
    "Расписание занятий\nна 2 семестр 2025-2026 учебного года.\nИнститут биотехнологии 2 курс": "6\n2\n0\n2\n3.\n0\n5.\n2\nа\nд\nе\nр\nС",
    "column_1": "08.30-10.00",
    "column_2": "",
    "column_3": ""
  },
  {
    "Расписание занятий\nна 2 семестр 2025-2026 учебного года.\nИнститут биотехнологии 2 курс": null,
    "column_1": "10.10-11.40",
    "column_2": "",
    "column_3": ""
  },
  {
    "Расписание занятий\nна 2 семестр 2025-2026 учебного года.\nИнститут биотехнологии 2 курс": null,
    "column_1": "12.00-13.30",
    "column_2": "",
    "column_3": "лаб.з. Структура пищевых систем кулинарной продукции\nдоц. Белова М.В. ауд. С-218"
  },
  {
    "Расписание занятий\nна 2 семестр 2025-2026 учебного года.\nИнститут биотехнологии 2 курс": null,
    "column_1": "13.40-15.10",
    "column_2": "лаб.з. Структура пищевых систем кулинарной продукции\nдоц. Белова М.В. ауд. С-218",
    "column_3": "пр.з. Философия\nдоц. Гижов В.А. ауд. С-208"
  },
  {
    "Расписание занятий\nна 2 семестр 2025-2026 учебного года.\nИнститут биотехнологии 2 курс": null,
    "column_1": "15.20-16.50",
    "column_2": "ЗАЧЕТ Санитария и гигиена питания\nпроф. Попова О.М. ауд. С-140",
    "column_3": "ЭКЗАМЕН Философия\nдоц. Гижов В.А. ауд. С-208"
  },
  {
    "Расписание занятий\nна 2 семестр 2025-2026 учебного года.\nИнститут биотехнологии 2 курс": null,
    "column_1": "17.00-18.30",
    "column_2": "ЭКЗАМЕН Философия\nдоц. Гижов В.А. ауд. С-208",
    "column_3": "ЗАЧЕТ Санитария и гигиена питания\nпроф. Попова О.М. ауд. С-140"
  },
  {
    "Расписание занятий\nна 2 семестр 2025-2026 учебного года.\nИнститут биотехнологии 2 курс": "6\n2\n0\n2\n3.\n0\n6.\n2\nг\nр\nе\nв\nт\nе\nЧ",
    "column_1": "08.30-10.00",
    "column_2": "",
    "column_3": ""
  },
  {
    "Расписание занятий\nна 2 семестр 2025-2026 учебного года.\nИнститут биотехнологии 2 курс": null,
    "column_1": "10.10-11.40",
    "column_2": "лаб.з. Электротехника\nдоц. Волгин А.В. учебный комплекс №2 ауд. 403",
    "column_3": ""
  },
  {
    "Расписание занятий\nна 2 семестр 2025-2026 учебного года.\nИнститут биотехнологии 2 курс": null,
    "column_1": "12.00-13.30",
    "column_2": "ЗАЧЕТ Электротехника\nдоц. Волгин А.В. учебный комплекс №2 ауд. 403",
    "column_3": "ЭКЗАМЕН Безопасность жизнедеятельности\nдоц. Карпова О.В. учебный комплекс №2 ауд. 307"
  },
  {
    "Расписание занятий\nна 2 семестр 2025-2026 учебного года.\nИнститут биотехнологии 2 курс": null,
    "column_1": "13.40-15.10",
    "column_2": "ЭКЗАМЕН Безопасность жизнедеятельности\nдоц. Карпова О.В. учебный комплекс №2 ауд. 208",
    "column_3": "лаб.з. Электротехника\nдоц. Волгин А.В. учебный комплекс №2 ауд. 403"
  },
  {
    "Расписание занятий\nна 2 семестр 2025-2026 учебного года.\nИнститут биотехнологии 2 курс": null,
    "column_1": "15.20-16.50",
    "column_2": "",
    "column_3": "ЗАЧЕТ Электротехника\nдоц. Волгин А.В. учебный комплекс №2 ауд. 403"
  },
  {
    "Расписание занятий\nна 2 семестр 2025-2026 учебного года.\nИнститут биотехнологии 2 курс": null,
    "column_1": "17.00-18.30",
    "column_2": "",
    "column_3": ""
  },
  {
    "Расписание занятий\nна 2 семестр 2025-2026 учебного года.\nИнститут биотехнологии 2 курс": "6\n2\n0\n2\n3.\n0\n7.\n2\nа\nц\nи\nн\nт\nя\nП",
    "column_1": "08.30-10.00",
    "column_2": "",
    "column_3": ""
  },
  {
    "Расписание занятий\nна 2 семестр 2025-2026 учебного года.\nИнститут биотехнологии 2 курс": null,
    "column_1": "10.10-11.40",
    "column_2": "ЭКЗАМЕН История России\nдоц. Федорова-Кузнецова И.В. ауд. 7",
    "column_3": "лаб.з. Структура пищевых систем кулинарной продукции\nдоц. Белова М.В. ауд. С-218"
  },
  {
    "Расписание занятий\nна 2 семестр 2025-2026 учебного года.\nИнститут биотехнологии 2 курс": null,
    "column_1": "12.00-13.30",
    "column_2": "",
    "column_3": "ЗАЧЕТ Структура пищевых систем кулинарной продукции\nдоц. Белова М.В. ауд. С-218"
  },
  {
    "Расписание занятий\nна 2 семестр 2025-2026 учебного года.\nИнститут биотехнологии 2 курс": null,
    "column_1": "13.40-15.10",
    "column_2": "лаб.з. Структура пищевых систем кулинарной продукции\nдоц. Белова М.В. ауд. С-218",
    "column_3": "ЭКЗАМЕН История России\nдоц. Федорова-Кузнецова И.В. ауд. 7"
  },
  {
    "Расписание занятий\nна 2 семестр 2025-2026 учебного года.\nИнститут биотехнологии 2 курс": null,
    "column_1": "15.20-16.50",
    "column_2": "ЗАЧЕТ Структура пищевых систем кулинарной продукции\nдоц. Белова М.В. ауд. С-218",
    "column_3": ""
  },
  {
    "Расписание занятий\nна 2 семестр 2025-2026 учебного года.\nИнститут биотехнологии 2 курс": null,
    "column_1": "17.00-18.30",
    "column_2": "",
    "column_3": ""
  },
  {
    "Расписание занятий\nна 2 семестр 2025-2026 учебного года.\nИнститут биотехнологии 2 курс": "а\nт\nо\nб\nб\nу\nС",
    "column_1": "08.30-10.00",
    "column_2": "",
    "column_3": ""
  },
  {
    "Расписание занятий\nна 2 семестр 2025-2026 учебного года.\nИнститут биотехнологии 2 курс": null,
    "column_1": "10.10-11.40",
    "column_2": "",
    "column_3": ""
  },
  {
    "Расписание занятий\nна 2 семестр 2025-2026 учебного года.\nИнститут биотехнологии 2 курс": null,
    "column_1": "12.00-13.30",
    "column_2": "",
    "column_3": ""
  },
  {
    "Расписание занятий\nна 2 семестр 2025-2026 учебного года.\nИнститут биотехнологии 2 курс": null,
    "column_1": "13.40-15.10",
    "column_2": "",
    "column_3": ""
  },
  {
    "Расписание занятий\nна 2 семестр 2025-2026 учебного года.\nИнститут биотехнологии 2 курс": null,
    "column_1": "15.20-16.50",
    "column_2": "",
    "column_3": ""
  },
  {
    "Расписание занятий\nна 2 семестр 2025-2026 учебного года.\nИнститут биотехнологии 2 курс": "",
    "column_1": null,
    "column_2": null,
    "column_3": null
  }
]