[
  {
    "Расписание занятий\nна 2 семестр 2025-2026 учебного года\nинститут инженерии и робототехники 3 курс": "Дни",
    "column_1": "Часы",
    "column_2": "Б-АИ-301 с 26.01.26"
  },
  {
    "Расписание занятий\nна 2 семестр 2025-2026 учебного года\nинститут инженерии и робототехники 3 курс": "к\nи\nн\nь\nл\nе\nд\nе\nн\nо\nП",
    "column_1": "8.30-10.00",
    "column_2": ""
  },
  {
    "Расписание занятий\nна 2 семестр 2025-2026 учебного года\nинститут инженерии и робототехники 3 курс": null,
    "column_1": "10.10-11.40",
    "column_2": "лек. УСТРОЙСТВО МАШИН И ОБОРУДОВАНИЯ В РАСТЕНИЕВОДСТВЕ\nдоц. Шардина Г.Е. 131"
  },
  {
    "Расписание занятий\nна 2 семестр 2025-2026 учебного года\nинститут инженерии и робототехники 3 курс": null,
    "column_1": "12.00-13.30",
    "column_2": "лаб.з. устройство машин и оборудования в растениеводстве\nШардина Г.Е. 131"
  },
  {
    "Расписание занятий\nна 2 семестр 2025-2026 учебного года\nинститут инженерии и робототехники 3 курс": null,
    "column_1": "13.40-15.10",
    "column_2": "лек. ЭКСПЛУАТАЦИЯ ТЕХНИЧЕСКИХ СРЕДСТВ В АПК\nпроф. Старцев А.С. 138"
  },
  {
    "Расписание занятий\nна 2 семестр 2025-2026 учебного года\nинститут инженерии и робототехники 3 курс": null,
    "column_1": "15.20-16.50",
    "column_2": "лаб.з. эксплуатация технических средств в АПК\nСтарцев А.С. Савенков А.С. Меденко А.А. 138"
  },
  {
    "Расписание занятий\nна 2 семестр 2025-2026 учебного года\nинститут инженерии и робототехники 3 курс": null,
    "column_1": "17.00-18.30",
    "column_2": ""
  },
  {
    "Расписание занятий\nна 2 семестр 2025-2026 учебного года\nинститут инженерии и робототехники 3 курс": "к\nи\nн\nр\nо\nт\nВ",
    "column_1": "8.30-10.00",
    "column_2": ""
  },
  {
    "Расписание занятий\nна 2 семестр 2025-2026 учебного года\nинститут инженерии и робототехники 3 курс": null,
    "column_1": "10.10-11.40",
    "column_2": "лаб.з. особенности изготовлениия деталей с применением CAD-CAM системы\nЧекмарев В.В. 520"
  },
  {
    "Расписание занятий\nна 2 семестр 2025-2026 учебного года\nинститут инженерии и робототехники 3 курс": null,
    "column_1": "12.00-13.30",
    "column_2": "лек. ТРАКТОРЫ И АВТОМОБИЛИ доц. Нестеров Е.С.33б"
  },
  {
    "Расписание занятий\nна 2 семестр 2025-2026 учебного года\nинститут инженерии и робототехники 3 курс": null,
    "column_1": null,
    "column_2": "лек. ПОДЪЕМНО-ТРАНСПОРТНЫЕ МАШИНЫ, ИХ УЗЛЫ И ДЕТАЛИ В АГРОИНЖЕНЕРИИ проф. Павлов П.И. 402"
  },
  {
    "Расписание занятий\nна 2 семестр 2025-2026 учебного года\nинститут инженерии и робототехники 3 курс": null,
    "column_1": "13.40-15.10",
    "column_2": "лаб.з. тракторы и автомобили\nДемин Е.Е. 33"
  },
  {
    "Расписание занятий\nна 2 семестр 2025-2026 учебного года\nинститут инженерии и робототехники 3 курс": null,
    "column_1": "15.20-16.50",
    "column_2": ""
  },
  {
    "Расписание занятий\nна 2 семестр 2025-2026 учебного года\nинститут инженерии и робототехники 3 курс": null,
    "column_1": "17.00-18.30",
    "column_2": ""
  },
  {
    "Расписание занятий\nна 2 семестр 2025-2026 учебного года\nинститут инженерии и робототехники 3 курс": "а\nд\nе\nр\nС",
    "column_1": "8.30-10.00",
    "column_2": "лаб.з. надежность технических систем в АПК\nИсмаилов И.С. 529"
  },
  {
    "Расписание занятий\nна 2 семестр 2025-2026 учебного года\nинститут инженерии и робототехники 3 курс": null,
    "column_1": "10.10-11.40",
    "column_2": "пр.з. подъемно-транспортные машины, их узлы и детали в агроинженерии\nПавлов П.И. 431"
  },
  {
    "Расписание занятий\nна 2 семестр 2025-2026 учебного года\nинститут инженерии и робототехники 3 курс": null,
    "column_1": "12.00-13.30",
    "column_2": "лек.ТЕХНИЧЕСКОЕ ОБОСНОВАНИЕ ИНЖЕНЕРНЫХ РЕШЕНИЙ проф.Чекмарев В.В. 33"
  },
  {
    "Расписание занятий\nна 2 семестр 2025-2026 учебного года\nинститут инженерии и робототехники 3 курс": null,
    "column_1": null,
    "column_2": "пр.з. техническое обоснование инженерных решений Чекмарев В.В. 33"
  },
  {
    "Расписание занятий\nна 2 семестр 2025-2026 учебного года\nинститут инженерии и робототехники 3 курс": null,
    "column_1": "13.40-15.10",
    "column_2": ""
  },
  {
    "Расписание занятий\nна 2 семестр 2025-2026 учебного года\nинститут инженерии и робототехники 3 курс": null,
    "column_1": "15.20-16.50",
    "column_2": ""
  },
  {
    "Расписание занятий\nна 2 семестр 2025-2026 учебного года\nинститут инженерии и робототехники 3 курс": null,
    "column_1": "17.00-18.30",
    "column_2": ""
  },
  {
    "Расписание занятий\nна 2 семестр 2025-2026 учебного года\nинститут инженерии и робототехники 3 курс": "г\nр\nе\nв\nт\nе\nЧ",
    "column_1": "8.30-10.00",
    "column_2": "лаб.з.подъемно-транспортные машины, их узлы и детали в агроинженерии Павлов П.И. 431"
  },
  {
    "Расписание занятий\nна 2 семестр 2025-2026 учебного года\nинститут инженерии и робототехники 3 курс": null,
    "column_1": null,
    "column_2": ""
  },
  {
    "Расписание занятий\nна 2 семестр 2025-2026 учебного года\nинститут инженерии и робототехники 3 курс": null,
    "column_1": "10.10-11.40",
    "column_2": "лек. НАДЕЖНОСТЬ ТЕХНИЧЕСКИХ СИСТЕМ В АПК\nдоц. Венскайтис В.В. 423"
  },
  {
    "Расписание занятий\nна 2 семестр 2025-2026 учебного года\nинститут инженерии и робототехники 3 курс": null,
    "column_1": "12.00-13.30",
    "column_2": "лек.ЭЛЕКТРОТЕХНИКА И ЭЛЕКТРОНИКА доц.Чернова Е.Н.413"
  },
  {
    "Расписание занятий\nна 2 семестр 2025-2026 учебного года\nинститут инженерии и робототехники 3 курс": null,
    "column_1": null,
    "column_2": "пр.з. электротехника и электроника Волгин А.В. 413"
  },
  {
    "Расписание занятий\nна 2 семестр 2025-2026 учебного года\nинститут инженерии и робототехники 3 курс": null,
    "column_1": "13.40-15.10",
    "column_2": "пр.з. общая физическая подготовка\nПяткина Н.А. сок"
  },
  {
    "Расписание занятий\nна 2 семестр 2025-2026 учебного года\nинститут инженерии и робототехники 3 курс": null,
    "column_1": "15.20-16.50",
    "column_2": ""
  },
  {
    "Расписание занятий\nна 2 семестр 2025-2026 учебного года\nинститут инженерии и робототехники 3 курс": null,
    "column_1": "17.00-18.30",
    "column_2": ""
  },
  {
    "Расписание занятий\nна 2 семестр 2025-2026 учебного года\nинститут инженерии и робототехники 3 курс": "а\nц\nи\nн\nт\nя\nП",
    "column_1": "8.30-10.00",
    "column_2": ""
  },
  {
    "Расписание занятий\nна 2 семестр 2025-2026 учебного года\nинститут инженерии и робототехники 3 курс": null,
    "column_1": "10.10-11.40",
    "column_2": "лек. ТЕХНОЛОГИЯ СЕЛЬСКОХОЗЯЙСТВЕННОГО МАШИНОСТРОЕНИЯ\nпроф. Чекмарев В.В. 115"
  },
  {
    "Расписание занятий\nна 2 семестр 2025-2026 учебного года\nинститут инженерии и робототехники 3 курс": null,
    "column_1": "12.00-13.30",
    "column_2": "лаб.з. технология сельскохозяйстенного машиностроения\nЧекмарев В.В. 115"
  },
  {
    "Расписание занятий\nна 2 семестр 2025-2026 учебного года\nинститут инженерии и робототехники 3 курс": null,
    "column_1": "13.40-15.10",
    "column_2": "лаб.з.технология сельскохозяйстенного машиностроения Чекмарев В.В. 33"
  },
  {
    "Расписание занятий\nна 2 семестр 2025-2026 учебного года\nинститут инженерии и робототехники 3 курс": null,
    "column_1": null,
    "column_2": "лек.ОСОБЕННОСТИ ИЗГОТОВЛЕНИЯ ДЕТАЛЕЙ С ПРИМЕНЕНИЕМ CAD-CAM СИСТЕМЫ проф.Чекмарев В.В.520"
  },
  {
    "Расписание занятий\nна 2 семестр 2025-2026 учебного года\nинститут инженерии и робототехники 3 курс": null,
    "column_1": "15.20-16.50",
    "column_2": "пр.з.надежность технических систем вАПК Березкин А.С. 529"
  },
  {
    "Расписание занятий\nна 2 семестр 2025-2026 учебного года\nинститут инженерии и робототехники 3 курс": null,
    "column_1": null,
    "column_2": ""
  },
  {
    "Расписание занятий\nна 2 семестр 2025-2026 учебного года\nинститут инженерии и робототехники 3 курс": null,
    "column_1": "17.00-18.30",
    "column_2": ""
  },
  {
    "Расписание занятий\nна 2 семестр 2025-2026 учебного года\nинститут инженерии и робототехники 3 курс": "а\nт\nо\nб",
    "column_1": "8.30-10.00",
    "column_2": ""
  },
  {
    "Расписание занятий\nна 2 семестр 2025-2026 учебного года\nинститут инженерии и робототехники 3 курс": null,
    "column_1": "10.10-11.40",
    "column_2": ""
  },
  {
    "Расписание занятий\nна 2 семестр 2025-2026 учебного года\nинститут инженерии и робототехники 3 курс": "б\nу\nС",
    "column_1": "12.00-13.30",
    "column_2": null
  },
  {
    "Расписание занятий\nна 2 семестр 2025-2026 учебного года\nинститут инженерии и робототехники 3 курс": "",
    "column_1": "13.40-15.10",
    "column_2": ""
  },
  {
    "Расписание занятий\nна 2 семестр 2025-2026 учебного года\nинститут инженерии и робототехники 3 курс": "",
    "column_1": null,
    "column_2": null
  }
]